[{"name":"Android 19","scores":[{"player":"coucou","score":157},{"player":"test","score":64},{"player":"Sim","score":45},{"player":"Elenora","score":31}],"tabTiles":[{"type":"game.model.Tree"},{"type":"game.model.Grass"},{"type":"game.model.Tree"},{"type":"game.model.Tree"},{"type":"game.model.Grass"},{"type":"game.model.Grass"},{"type":"game.model.Grass"},{"type":"game.model.Tree"},{"type":"game.model.Tree"},{"type":"game.model.Grass"},{"type":"game.model.Grass"},{"type":"game.model.Grass"},{"type":"game.model.Water"},{"type":"game.model.Water"},{"type":"game.model.Water"},{"type":"game.model.Water"},{"type":"game.model.Water"},{"type":"game.model.Tree"},{"type":"game.model.Grass"},{"type":"game.model.Grass"},{"type":"game.model.Grass"},{"type":"game.model.Tree"},{"type":"game.model.Water"},{"type":"game.model.Tree"},{"type":"game.model.Grass"},{"type":"game.model.Tree"},{"type":"game.model.Grass"},{"type":"game.model.Grass"},{"type":"game.model.Tree"},{"type":"game.model.Tree"},{"type":"game.model.Grass"},{"type":"game.model.Water"},{"type":"game.model.Grass"},{"type":"game.model.Grass"},{"type":"game.model.Grass"},{"type":"game.model.Water"},{"type":"game.model.Water"},{"type":"game.model.Water"},{"type":"game.model.Tree"},{"type":"game.model.Grass"},{"type":"game.model.Tree"},{"type":"game.model.Tree"},{"type":"game.model.Tree"},{"type":"game.model.Water"},{"type":"game.model.Grass"},{"type":"game.model.Grass"},{"type":"game.model.Water"},{"type":"game.model.Grass"},{"type":"game.model.Water"},{"type":"game.model.Water"},{"type":"game.model.Water"},{"type":"game.model.Grass"},{"type":"game.model.Water"},{"type":"game.model.Grass"},{"type":"game.model.Water"},{"type":"game.model.Tree"},{"type":"game.model.Grass"},{"type":"game.model.Grass"},{"type":"game.model.Water"},{"type":"game.model.Tree"},{"type":"game.model.Grass"},{"type":"game.model.Tree"},{"type":"game.model.Grass"},{"type":"game.model.Tree"},{"type":"game.model.Grass"},{"type":"game.model.Grass"},{"type":"game.model.Water"},{"type":"game.model.Tree"},{"type":"game.model.Grass"},{"type":"game.model.Water"},{"type":"game.model.Grass"},{"type":"game.model.Tree"},{"type":"game.model.Water"},{"type":"game.model.Tree"},{"type":"game.model.Water"},{"type":"game.model.Tree"},{"type":"game.model.Tree"},{"type":"game.model.Grass"},{"type":"game.model.Tree"},{"type":"game.model.Water"},{"type":"game.model.Grass"},{"type":"game.model.Grass"},{"type":"game.model.Grass"},{"type":"game.model.Water"},{"type":"game.model.Tree"},{"type":"game.model.Tree"},{"type":"game.model.Grass"},{"type":"game.model.Grass"},{"type":"game.model.Water"},{"type":"game.model.Grass"},{"type":"game.model.Grass"},{"type":"game.model.Tree"},{"type":"game.model.Grass"},{"type":"game.model.Grass"},{"type":"game.model.Water"},{"type":"game.model.Water"},{"type":"game.model.Water"},{"type":"game.model.Tree"},{"type":"game.model.Tree"},{"type":"game.model.Tree"}],"commandsCollectors":[{"playerName":"Sim","commands":[{"type":"game.model.PutCityBlock","position":-1,"x":8,"y":6,"typeCityBlock":-1,"mementoHasMovedBlock":false,"mementoTypeMoveBlock":0,"mementoPosMoveBlock":0,"mementoAvailableCityBlock":[0,1,0,0],"mementoCityBlockSelected":1,"mementoNomJoueur":"Sim","mementoScore":0,"mementoNextScore":10,"mementoGameOver":false},{"type":"game.model.PutCityBlock","position":-1,"x":7,"y":5,"typeCityBlock":-1,"mementoHasMovedBlock":false,"mementoTypeMoveBlock":0,"mementoPosMoveBlock":0,"mementoAvailableCityBlock":[1,1,1,1],"mementoCityBlockSelected":1,"mementoNomJoueur":"Sim","mementoScore":17,"mementoNextScore":20,"mementoGameOver":false},{"type":"game.model.PutCityBlock","position":-1,"x":7,"y":4,"typeCityBlock":-1,"mementoHasMovedBlock":false,"mementoTypeMoveBlock":0,"mementoPosMoveBlock":0,"mementoAvailableCityBlock":[3,2,3,3],"mementoCityBlockSelected":1,"mementoNomJoueur":"Sim","mementoScore":31,"mementoNextScore":40,"mementoGameOver":false}]},{"playerName":"test","commands":[{"type":"game.model.PutCityBlock","position":-1,"x":7,"y":8,"typeCityBlock":-1,"mementoHasMovedBlock":false,"mementoTypeMoveBlock":0,"mementoPosMoveBlock":0,"mementoAvailableCityBlock":[0,1,0,0],"mementoCityBlockSelected":1,"mementoNomJoueur":"test","mementoScore":0,"mementoNextScore":10,"mementoGameOver":false},{"type":"game.model.PutCityBlock","position":-1,"x":6,"y":8,"typeCityBlock":-1,"mementoHasMovedBlock":false,"mementoTypeMoveBlock":0,"mementoPosMoveBlock":0,"mementoAvailableCityBlock":[2,2,2,2],"mementoCityBlockSelected":1,"mementoNomJoueur":"test","mementoScore":21,"mementoNextScore":30,"mementoGameOver":false},{"type":"game.model.PutCityBlock","position":-1,"x":5,"y":6,"typeCityBlock":-1,"mementoHasMovedBlock":false,"mementoTypeMoveBlock":0,"mementoPosMoveBlock":0,"mementoAvailableCityBlock":[4,3,4,4],"mementoCityBlockSelected":1,"mementoNomJoueur":"test","mementoScore":47,"mementoNextScore":50,"mementoGameOver":false}]},{"playerName":"coucou","commands":[{"type":"game.model.PutCityBlock","position":-1,"x":7,"y":8,"typeCityBlock":-1,"mementoHasMovedBlock":false,"mementoTypeMoveBlock":0,"mementoPosMoveBlock":0,"mementoAvailableCityBlock":[0,1,0,0],"mementoCityBlockSelected":1,"mementoNomJoueur":"test3","mementoScore":0,"mementoNextScore":10,"mementoGameOver":false},{"type":"game.model.PutCityBlock","position":-1,"x":5,"y":6,"typeCityBlock":-1,"mementoHasMovedBlock":false,"mementoTypeMoveBlock":0,"mementoPosMoveBlock":0,"mementoAvailableCityBlock":[2,2,2,2],"mementoCityBlockSelected":1,"mementoNomJoueur":"test3","mementoScore":21,"mementoNextScore":30,"mementoGameOver":false},{"type":"game.model.PutCityBlock","position":-1,"x":4,"y":4,"typeCityBlock":-1,"mementoHasMovedBlock":false,"mementoTypeMoveBlock":0,"mementoPosMoveBlock":0,"mementoAvailableCityBlock":[3,2,3,3],"mementoCityBlockSelected":1,"mementoNomJoueur":"test3","mementoScore":38,"mementoNextScore":40,"mementoGameOver":false},{"type":"game.model.PutCityBlock","position":-1,"x":8,"y":6,"typeCityBlock":-1,"mementoHasMovedBlock":false,"mementoTypeMoveBlock":0,"mementoPosMoveBlock":0,"mementoAvailableCityBlock":[4,2,4,4],"mementoCityBlockSelected":2,"mementoNomJoueur":"test3","mementoScore":47,"mementoNextScore":50,"mementoGameOver":false},{"type":"game.model.PutCityBlock","position":-1,"x":7,"y":4,"typeCityBlock":-1,"mementoHasMovedBlock":false,"mementoTypeMoveBlock":0,"mementoPosMoveBlock":0,"mementoAvailableCityBlock":[6,4,5,6],"mementoCityBlockSelected":2,"mementoNomJoueur":"test3","mementoScore":63,"mementoNextScore":70,"mementoGameOver":false},{"type":"game.model.MoveCityBlock","x":4,"y":0,"posBefore":-1,"posAfter":-1,"mementoHasMovedBlock":false,"mementoTypeMoveBlock":5,"mementoPosMoveBlock":47,"mementoAvailableCityBlock":[7,5,5,7],"mementoCityBlockSelected":2,"mementoNomJoueur":"test3","mementoScore":71,"mementoNextScore":80,"mementoGameOver":false},{"type":"game.model.PutCityBlock","position":-1,"x":7,"y":5,"typeCityBlock":-1,"mementoHasMovedBlock":true,"mementoTypeMoveBlock":0,"mementoPosMoveBlock":47,"mementoAvailableCityBlock":[7,5,5,7],"mementoCityBlockSelected":3,"mementoNomJoueur":"test3","mementoScore":79,"mementoNextScore":80,"mementoGameOver":false},{"type":"game.model.PutCityBlock","position":-1,"x":7,"y":4,"typeCityBlock":-1,"mementoHasMovedBlock":true,"mementoTypeMoveBlock":0,"mementoPosMoveBlock":47,"mementoAvailableCityBlock":[11,9,9,10],"mementoCityBlockSelected":3,"mementoNomJoueur":"test3","mementoScore":114,"mementoNextScore":120,"mementoGameOver":false},{"type":"game.model.CommandRename","nouveauNomJoueur":"coucou","mementoNomJoueur":"test3"}]},{"playerName":"Elenora","commands":[{"type":"game.model.PutCityBlock","position":-1,"x":4,"y":3,"typeCityBlock":-1,"mementoHasMovedBlock":false,"mementoTypeMoveBlock":0,"mementoPosMoveBlock":0,"mementoAvailableCityBlock":[0,1,0,0],"mementoCityBlockSelected":1,"mementoNomJoueur":"Elenora","mementoScore":0,"mementoNextScore":10,"mementoGameOver":false},{"type":"game.model.PutCityBlock","position":-1,"x":3,"y":3,"typeCityBlock":-1,"mementoHasMovedBlock":false,"mementoTypeMoveBlock":0,"mementoPosMoveBlock":0,"mementoAvailableCityBlock":[1,1,1,1],"mementoCityBlockSelected":1,"mementoNomJoueur":"Elenora","mementoScore":13,"mementoNextScore":20,"mementoGameOver":false}]}],"topScores":[{"player":"coucou","score":157},{"player":"test","score":64},{"player":"Sim","score":45},{"player":"Elenora","score":31}]}]